pcbu/__init__.py
pcbu/__main__.py
pcbu/crypto.py
pcbu/helpers.py
pcbu/models.py
pcbu/tcp/common.py
pcbu/tcp/pair_client.py
pcbu/tcp/pair_server.py
pcbu/tcp/unlock_client.py
pcbu/tcp/unlock_server.py
py_pcbu-0.5.0.dist-info/METADATA
py_pcbu-0.5.0.dist-info/WHEEL
py_pcbu-0.5.0.dist-info/licenses/LICENSE
py_pcbu-0.5.0.dist-info/RECORD
