Metadata-Version: 2.3
Name: py-pcbu
Version: 0.5.0
Summary: A package to interact with the PC Bio Unlock credentials module.
Project-URL: Homepage, https://github.com/lmgarret/py-pcbu
Project-URL: Repository, https://github.com/lmgarret/py-pcbu.git
Project-URL: Issues, https://github.com/lmgarret/py-pcbu/issues
Project-URL: Changelog, https://github.com/lmgarret/py-pcbu/blob/master/CHANGELOG.md
Author-email: "LM. Garret" <lm@codingarret.dev>
Requires-Python: >=3.8
Requires-Dist: cryptography>=43.0.1
Requires-Dist: dataclass-wizard>=0.23.0
Requires-Dist: py-machineid>=0.6.0
Provides-Extra: cli
Requires-Dist: qrcode>=7.4.2; extra == 'cli'
Requires-Dist: typer>=0.12.5; extra == 'cli'
